LICENSE
LICENSE_pyadm1.txt
README.md
setup.py
anaerodig/__init__.py
anaerodig/nb_typ.py
anaerodig/np_typ.py
anaerodig.egg-info/PKG-INFO
anaerodig.egg-info/SOURCES.txt
anaerodig.egg-info/dependency_links.txt
anaerodig.egg-info/requires.txt
anaerodig.egg-info/top_level.txt
anaerodig/convert/__init__.py
anaerodig/convert/feed_convert.py
anaerodig/convert/adm1_to_am2/__init__.py
anaerodig/convert/adm1_to_am2/feed_convert.py
anaerodig/ode_solver/__init__.py
anaerodig/ode_solver/runge_kutta.py
anaerodig/pyad/__init__.py
anaerodig/pyad/config.py
anaerodig/pyad/digester.py
anaerodig/pyad/feed.py
anaerodig/pyad/states.py
anaerodig/pyadm1/__init__.py
anaerodig/pyadm1/der_adm1.py
anaerodig/pyadm1/digester.py
anaerodig/pyadm1/prediction_error.py
anaerodig/pyadm1/basic_classes/Phy.py
anaerodig/pyadm1/basic_classes/__init__.py
anaerodig/pyadm1/basic_classes/config.py
anaerodig/pyadm1/basic_classes/feed.py
anaerodig/pyadm1/basic_classes/param.py
anaerodig/pyadm1/basic_classes/state.py
anaerodig/pyadm1/data/DIG_CONFIG.json
anaerodig/pyadm1/data/FEED.csv
anaerodig/pyadm1/data/INI_STATE.json
anaerodig/pyadm1/data/PARAM.json
anaerodig/pyadm1/data/__init__.py
anaerodig/pyadm1/model/__init__.py
anaerodig/pyadm1/model/helpers.py
anaerodig/pyadm1/model/run_adm1.py
anaerodig/pyadm1/model/vs_computation.py
anaerodig/pyadm1/num_space/__init__.py
anaerodig/pyadm1/num_space/num_space.py
anaerodig/pyam2/__init__.py
anaerodig/pyam2/digester.py
anaerodig/pyam2/basic_classes/__init__.py
anaerodig/pyam2/basic_classes/config.py
anaerodig/pyam2/basic_classes/feed.py
anaerodig/pyam2/basic_classes/param.py
anaerodig/pyam2/basic_classes/states.py
anaerodig/pyam2/data/FEED.csv
anaerodig/pyam2/data/INI_STATE.json
anaerodig/pyam2/data/OBS.csv
anaerodig/pyam2/data/PARAM.json
anaerodig/pyam2/data/__init__.py
anaerodig/pyam2/model/__init__.py
anaerodig/pyam2/model/der_am2.py
anaerodig/pyam2/model/run_am2.py
anaerodig/pyam2/num_space/__init__.py
anaerodig/pyam2/num_space/num_space.py